btgatt/__init__.py
btgatt/characteristic.py
btgatt/client.py
btgatt/client_exceptions.py
btgatt/gap.py
btgatt/gatt.py
btgatt/service.py
btgatt/uuids.py
btgatt/pytransform/__init__.py
btgatt/pytransform/platforms/linux/aarch64/_pytransform.so
btgatt/pytransform/platforms/linux/x86_64/_pytransform.so
btgatt/res/appearance_values.json
btgatt/res/gatt_attr_types.json
btgatt/server/__init__.py
btgatt/server/__main__.py
btgatt/server/advertisement.py
btgatt/server/advertiser.sh
btgatt/server/agent.py
btgatt/server/common.py
btgatt/server/example_service.py
btgatt/server/gatt.py
btgatt/server/generic_access_service.py
btgatt/server/generic_attribute_service.py
btgatt/server/test_service.py
btgatt/server/ui.py
btgatt-0.0.22.dist-info/LICENSE.txt
btgatt-0.0.22.dist-info/METADATA
btgatt-0.0.22.dist-info/WHEEL
btgatt-0.0.22.dist-info/top_level.txt
btgatt-0.0.22.dist-info/RECORD
