Metadata-Version: 2.1
Name: btgatt
Version: 0.0.22
Summary: Bluetooth GATT Utilities
Home-page: https://pypi.org/project/btgatt
Author: Cibo
Author-email: cibo@bio-electric.com
License: Proprietary
Classifier: Operating System :: POSIX :: Linux
Classifier: Programming Language :: Python :: 3
Classifier: Programming Language :: Python :: 3 :: Only
Classifier: Programming Language :: Python :: 3.10
Classifier: License :: Other/Proprietary License
Requires-Python: ==3.10.*
License-File: LICENSE.txt
Requires-Dist: btatt (>=0.0.19)
Requires-Dist: xpycommon (>=0.0.23)
